django_simplecaptcha-1.0.0.dist-info/DESCRIPTION.rst
django_simplecaptcha-1.0.0.dist-info/METADATA
django_simplecaptcha-1.0.0.dist-info/RECORD
django_simplecaptcha-1.0.0.dist-info/WHEEL
django_simplecaptcha-1.0.0.dist-info/metadata.json
django_simplecaptcha-1.0.0.dist-info/top_level.txt
simplecaptcha/__init__.py
simplecaptcha/decorators.py
simplecaptcha/fields.py
simplecaptcha/settings.py
simplecaptcha/widgets.py
