Metadata-Version: 2.0
Name: django-simplecaptcha
Version: 1.0.0
Summary: A simple math-based captcha for Django forms
Home-page: https://github.com/Kromey/django-simplecaptcha
Author: Travis Veazey
Author-email: travisvz@gmail.com
License: MIT
Keywords: django simple math captcha
Platform: UNKNOWN
Classifier: Development Status :: 5 - Production/Stable
Classifier: Intended Audience :: Developers
Classifier: Framework :: Django
Classifier: Framework :: Django :: 1.7
Classifier: License :: OSI Approved :: MIT License
Classifier: Programming Language :: Python :: 3
Classifier: Programming Language :: Python :: 3.2
Classifier: Programming Language :: Python :: 3.3
Classifier: Programming Language :: Python :: 3.4
Classifier: Programming Language :: Python :: 3 :: Only
Requires-Dist: django (>=1.7)
